tuf_on_ci_sign/__init__.py
tuf_on_ci_sign/_common.py
tuf_on_ci_sign/_signer_repository.py
tuf_on_ci_sign/_user.py
tuf_on_ci_sign/delegate.py
tuf_on_ci_sign/import_repo.py
tuf_on_ci_sign/sign.py
tuf_on_ci_sign-0.18.0.dist-info/METADATA
tuf_on_ci_sign-0.18.0.dist-info/WHEEL
tuf_on_ci_sign-0.18.0.dist-info/entry_points.txt
tuf_on_ci_sign-0.18.0.dist-info/licenses/LICENSE
tuf_on_ci_sign-0.18.0.dist-info/RECORD
